vvv11inf35706/__init__.py
vvv11inf35706-1.0.dist-info/METADATA
vvv11inf35706-1.0.dist-info/WHEEL
vvv11inf35706-1.0.dist-info/top_level.txt
vvv11inf35706-1.0.dist-info/RECORD
