Metadata-Version: 2.1
Name: vvv11inf35706
Version: 1.0
Summary: flskdzhgby
Home-page: UNKNOWN
Author: vvv06357
Author-email: valery.ovechey@gmail.com
License: UNKNOWN
Platform: UNKNOWN
Classifier: Programming Language :: Python :: 3
Classifier: License :: OSI Approved :: MIT License
Classifier: Operating System :: OS Independent
Requires-Python: >=3.6
